tacho/__init__.py
tacho/ai.py
tacho/cli.py
tacho/config.py
tacho/display.py
tacho-0.8.8.dist-info/METADATA
tacho-0.8.8.dist-info/WHEEL
tacho-0.8.8.dist-info/entry_points.txt
tacho-0.8.8.dist-info/RECORD
