Metadata-Version: 2.4
Name: tacho
Version: 0.8.8
Summary: CLI tool for measuring and comparing LLM inference speeds
Project-URL: Homepage, https://github.com/pietz/tacho
Project-URL: Repository, https://github.com/pietz/tacho
Project-URL: Issues, https://github.com/pietz/tacho/issues
Author-email: Paul-Louis Pröve <mail@plpp.de>
License-Expression: MIT
Keywords: benchmark,cli,inference,llm,performance
Classifier: Development Status :: 3 - Alpha
Classifier: Intended Audience :: Developers
Classifier: License :: OSI Approved :: MIT License
Classifier: Programming Language :: Python :: 3
Classifier: Programming Language :: Python :: 3.10
Classifier: Programming Language :: Python :: 3.11
Classifier: Programming Language :: Python :: 3.12
Classifier: Topic :: Scientific/Engineering :: Artificial Intelligence
Classifier: Topic :: Software Development :: Libraries :: Python Modules
Requires-Python: >=3.10
Requires-Dist: boto3>=1.38.46
Requires-Dist: google-auth>=2.40.3
Requires-Dist: google-cloud-aiplatform>=1.100.0
Requires-Dist: google>=3.0.0
Requires-Dist: litellm>=1.80.10
Requires-Dist: python-dotenv>=1.1.1
Requires-Dist: rich>=14.0.0
Requires-Dist: typer>=0.16.0
